ab_service/template/__init__.py
ab_service/template/main.py
ab_service/template/models/__init__.py
ab_service/template/models/heartbeat.py
ab_service/template/routes/__init__.py
ab_service/template/routes/heartbeat.py
ab_template_service-0.3.0.dist-info/METADATA
ab_template_service-0.3.0.dist-info/WHEEL
ab_template_service-0.3.0.dist-info/licenses/LICENSE
ab_template_service-0.3.0.dist-info/RECORD
